Workbook

Sheet Dataset
A1: TransactionID | B1: Date | C1: Time | D1: CustomerID | E1: CustomerName | F1: Gender | G1: Age | H1: Region | I1: City | J1: Category | K1: Product | L1: Quantity | M1: UnitPrice | N1: Discount | O1: Revenue | P1: Cost | Q1: Profit | R1: PaymentMethod | S1: Salesperson | T1: CustomerType | U1: Rating | V1: YEAR | W1: MONTH | X1: PROFIT MARGIN | Y1: UPPER_CASE | Z1: FIRST NAME
A2: T0001 | B2: 45916 | C2: 12:20 | D2: C029 | E2: Avni Patel | F2: Male | G2: 51 | H2: West | I2: Vadodara | J2: Fashion | K2: Sneakers | L2: 2 | M2: 2805.42 | N2: 0.05 | O2: 5330.3 | P2: 3676.48 | Q2: 1653.82 | R2: Cash | S2: Amit | T2: Returning | U2: 4 | V2: {=YEAR(B2:B251)} -> 2025 | W2: =TEXT(B2,"mmm") -> Sep | X2: =IFERROR(Q2/O2,0) -> 0.31026771 | Y2: =UPPER(Table1[[#This Row],[CustomerName]]) -> AVNI PATEL | Z2: =LEFT(E2,FIND( " ",E2)-1) -> Avni
A3: T0002 | B3: 46017 | C3: 09:15 | D3: C018 | E3: Isha Patel | F3: Female | G3: 35 | H3: North | I3: Chandigarh | J3: Home | K3: Mixer Grinder | L3: 2 | M3: 3737.83 | N3: 0.15 | O3: 6354.31 | P3: 4823.92 | Q3: 1530.39 | R3: Cash | S3: Neha | T3: VIP | U3: 4 | V3: 2025 | W3: =TEXT(B3,"mmm") -> Dec | X3: =IFERROR(Q3/O3,0) -> 0.24084283 | Y3: =UPPER(Table1[[#This Row],[CustomerName]]) -> ISHA PATEL | Z3: =LEFT(E3,FIND( " ",E3)-1) -> Isha
A4: T0003 | B4: 45659 | C4: 09:50 | D4: C049 | E4: Riya Shah | F4: Male | G4: 41 | H4: South | I4: Kochi | J4: Grocery | K4: Coffee | L4: 5 | M4: 477.55 | N4: 0 | O4: 2387.75 | P4: 1613.58 | Q4: 774.17 | R4: Debit Card | S4: Karan | T4: VIP | U4: 4 | V4: 2025 | W4: =TEXT(B4,"mmm") -> Jan | X4: =IFERROR(Q4/O4,0) -> 0.32422574 | Y4: =UPPER(Table1[[#This Row],[CustomerName]]) -> RIYA SHAH | Z4: =LEFT(E4,FIND( " ",E4)-1) -> Riya
A5: T0004 | B5: 45773 | C5: 19:00 | D5: C033 | E5: Aditya Shah | F5: Female | G5: 22 | H5: West | I5: Surat | J5: Electronics | K5: Smartphone | L5: 4 | M5: 30387.3 | N5: 0.15 | O5: 103316.82 | P5: 83482.75 | Q5: 19834.07 | R5: UPI | S5: Vivek | T5: New | U5: 4 | V5: 2025 | W5: =TEXT(B5,"mmm") -> Apr | X5: =IFERROR(Q5/O5,0) -> 0.19197329 | Y5: =UPPER(Table1[[#This Row],[CustomerName]]) -> ADITYA SHAH | Z5: =LEFT(E5,FIND( " ",E5)-1) -> Aditya
A6: T0005 | B6: 45967 | C6: 11:50 | D6: C002 | E6: Vivaan Patel | F6: Female | G6: 56 | H6: West | I6: Surat | J6: Grocery | K6: Protein Bar | L6: 1 | M6: 230.72 | N6: 0.15 | O6: 196.11 | P6: 134.35 | Q6: 61.76 | R6: Cash | S6: Karan | T6: Returning | U6: 4 | V6: 2025 | W6: =TEXT(B6,"mmm") -> Nov | X6: =IFERROR(Q6/O6,0) -> 0.3149253 | Y6: =UPPER(Table1[[#This Row],[CustomerName]]) -> VIVAAN PATEL | Z6: =LEFT(E6,FIND( " ",E6)-1) -> Vivaan
A7: T0006 | B7: 45679 | C7: 14:40 | D7: C012 | E7: Kabir Patel | F7: Female | G7: 31 | H7: North | I7: Delhi | J7: Home | K7: Air Fryer | L7: 3 | M7: 6431.77 | N7: 0.1 | O7: 17365.78 | P7: 12512.52 | Q7: 4853.26 | R7: Cash | S7: Amit | T7: New | U7: 5 | V7: 2025 | W7: =TEXT(B7,"mmm") -> Jan | X7: =IFERROR(Q7/O7,0) -> 0.27947262 | Y7: =UPPER(Table1[[#This Row],[CustomerName]]) -> KABIR PATEL | Z7: =LEFT(E7,FIND( " ",E7)-1) -> Kabir
A8: T0007 | B8: 45661 | C8: 11:50 | D8: C019 | E8: Riya Patel | F8: Female | G8: 53 | H8: South | I8: Chennai | J8: Fashion | K8: T-Shirt | L8: 4 | M8: 963.43 | N8: 0.1 | O8: 3468.35 | P8: 2344.3 | Q8: 1124.05 | R8: Debit Card | S8: Pooja | T8: New | U8: 5 | V8: 2025 | W8: =TEXT(B8,"mmm") -> Jan | X8: =IFERROR(Q8/O8,0) -> 0.32408782 | Y8: =UPPER(Table1[[#This Row],[CustomerName]]) -> RIYA PATEL | Z8: =LEFT(E8,FIND( " ",E8)-1) -> Riya
A9: T0008 | B9: 45959 | C9: 13:45 | D9: C049 | E9: Riya Shah | F9: Male | G9: 41 | H9: South | I9: Kochi | J9: Grocery | K9: Coffee | L9: 4 | M9: 435.2 | N9: 0.1 | O9: 1566.72 | P9: 1031.19 | Q9: 535.53 | R9: UPI | S9: Karan | T9: New | U9: 4 | V9: 2025 | W9: =TEXT(B9,"mmm") -> Oct | X9: =IFERROR(Q9/O9,0) -> 0.34181602 | Y9: =UPPER(Table1[[#This Row],[CustomerName]]) -> RIYA SHAH | Z9: =LEFT(E9,FIND( " ",E9)-1) -> Riya
A10: T0009 | B10: 45711 | C10: 18:15 | D10: C031 | E10: Aarav Shah | F10: Male | G10: 39 | H10: West | I10: Vadodara | J10: Fashion | K10: Backpack | L10: 2 | M10: 1527.6 | N10: 0.15 | O10: 2596.92 | P10: 1796.37 | Q10: 800.55 | R10: Debit Card | S10: Neha | T10: VIP | U10: 5 | V10: 2025 | W10: =TEXT(B10,"mmm") -> Feb | X10: =IFERROR(Q10/O10,0) -> 0.30826903 | Y10: =UPPER(Table1[[#This Row],[CustomerName]]) -> AARAV SHAH | Z10: =LEFT(E10,FIND( " ",E10)-1) -> Aarav
A11: T0010 | B11: 45956 | C11: 14:50 | D11: C033 | E11: Aditya Shah | F11: Female | G11: 22 | H11: West | I11: Surat | J11: Fashion | K11: Jeans | L11: 2 | M11: 1889.31 | N11: 0 | O11: 3778.62 | P11: 2804.88 | Q11: 973.74 | R11: Cash | S11: Neha | T11: New | U11: 5 | V11: 2025 | W11: =TEXT(B11,"mmm") -> Oct | X11: =IFERROR(Q11/O11,0) -> 0.25769725 | Y11: =UPPER(Table1[[#This Row],[CustomerName]]) -> ADITYA SHAH | Z11: =LEFT(E11,FIND( " ",E11)-1) -> Aditya
A12: T0011 | B12: 45978 | C12: 16:50 | D12: C020 | E12: Priya Patel | F12: Female | G12: 25 | H12: West | I12: Mumbai | J12: Home | K12: Air Fryer | L12: 4 | M12: 6902.08 | N12: 0.08 | O12: 25399.65 | P12: 18688.38 | Q12: 6711.27 | R12: Debit Card | S12: Amit | T12: New | U12: 5 | V12: 2025 | W12: =TEXT(B12,"mmm") -> Nov | X12: =IFERROR(Q12/O12,0) -> 0.26422687 | Y12: =UPPER(Table1[[#This Row],[CustomerName]]) -> PRIYA PATEL | Z12: =LEFT(E12,FIND( " ",E12)-1) -> Priya
A13: T0012 | B13: 45971 | C13: 18:40 | D13: C022 | E13: Mahi Patel | F13: Female | G13: 41 | H13: South | I13: Chennai | J13: Electronics | K13: Smartphone | L13: 3 | M13: 28209.89 | N13: 0 | O13: 84629.67 | P13: 66482.85 | Q13: 18146.82 | R13: Cash | S13: Pooja | T13: VIP | U13: 4 | V13: 2025 | W13: =TEXT(B13,"mmm") -> Nov | X13: =IFERROR(Q13/O13,0) -> 0.21442622 | Y13: =UPPER(Table1[[#This Row],[CustomerName]]) -> MAHI PATEL | Z13: =LEFT(E13,FIND( " ",E13)-1) -> Mahi
A14: T0013 | B14: 46022 | C14: 12:40 | D14: C006 | E14: Rohan Patel | F14: Male | G14: 38 | H14: West | I14: Ahmedabad | J14: Fashion | K14: Sneakers | L14: 4 | M14: 2635.47 | N14: 0.02 | O14: 10331.04 | P14: 7472.03 | Q14: 2859.01 | R14: Debit Card | S14: Amit | T14: Returning | U14: 4 | V14: 2025 | W14: =TEXT(B14,"mmm") -> Dec | X14: =IFERROR(Q14/O14,0) -> 0.27673981 | Y14: =UPPER(Table1[[#This Row],[CustomerName]]) -> ROHAN PATEL | Z14: =LEFT(E14,FIND( " ",E14)-1) -> Rohan
... A251: T0250 | B251: 45741 | C251: 10:20 | D251: C042 | E251: Kabir Shah | F251: Female | G251: 37 | H251: West | I251: Vadodara | J251: Electronics | K251: Smartwatch | L251: 1 | M251: 4836.56 | N251: 0.15 | O251: 4111.08 | P251: 2719.13 | Q251: 1391.95 | R251: UPI | S251: Karan | T251: New | U251: 5 | V251: 2025 | W251: =TEXT(B251,"mmm") -> Mar | X251: =IFERROR(Q251/O251,0) -> 0.33858499 | Y251: =UPPER(Table1[[#This Row],[CustomerName]]) -> KABIR SHAH | Z251: =LEFT(E251,FIND( " ",E251)-1) -> Kabir

Sheet KPI
A1: KPI Summary Metrics
A3: TOTAL TRANSACTION | B3: =IFERROR(COUNTA(Dataset!A2:A251),0) -> 250
A4: TOTAL REVENUE | B4: =SUM(Dataset!O2:O251) -> 6903164.1
A5: AVERAGE PROFIT MARGIN | B5: =AVERAGE(Dataset!Q2:Q251) -> 7866.764
A6: TOTAL COST | B6: =IFERROR(SUM(Dataset!P2:P251),0) -> 4936473.1
A7: TOTAL PROFIT | B7: =IFERROR(SUM(Dataset!Q2:Q251),0) -> 1966691
A8: TOTAL QUANTITY | B8: =IFERROR(SUM(Dataset!L2:L251),0) -> 747
A9: AVERAGE RATING | B9: =IFERROR(AVERAGE(Dataset!U2:U251),0) -> 4.236
A10: PROFIT MARGIN | B10: =IFERROR(SUM(Dataset!Q2:Q251)/SUM(Dataset!O2:O251),0) -> 0.28489703

Sheet HIGH-VALUE CUSTOMERS
A1: HIGH-VALUE CUSTOMER
A3: TOP 10 HIGH-VALUE CUSTOMER BY REVENUE | E3: MOST PURCHASED PRODUCT
A5: {=_xlfn.CHOOSEROWS(_xlfn._xlws.SORT(_xlfn.HSTACK(_xlfn.UNIQUE(Dataset!E2:E250), SUMIFS(Dataset!O2:O250, Dataset!E2:E250, _xlfn.UNIQUE(Dataset!E2:E250))), 2, -1), _xlfn.SEQUENCE(10))} -> Kavya Patel | B5: 785542.24 | E5: {=INDEX(Dataset!K2:K250, MODE(MATCH(Dataset!K2:K250, Dataset!K2:K250, 0)))} -> Laptop
A6: Dev Shah | B6: 625417.68
A7: Ishaan Shah | B7: 304143.57
A8: Rohan Shah | B8: 288697.45
A9: Kavya Shah | B9: 287541.58
A10: Riya Shah | B10: 285679.52
A11: Jiya Patel | B11: 280732.81
A12: Avni Shah | B12: 274760.96
A13: Priya Shah | B13: 268725.62
A14: Anaya Shah | B14: 265947.38
A18: UNIQUE CUSTOMER LIST
A19: NAME | B19: PROFIT | C19: QUANTITY | D19: CUSTOMER TYPE
A20: {=_xlfn.UNIQUE(Dataset!E2:E250)} -> Avni Patel | B20: =IFERROR(SUMIF(Dataset!E:E,A20,Dataset!Q:Q),0) -> 49235.89 | C20: =IFERROR(SUMIF(Dataset!E:E,A20,Dataset!L:L),0) -> 11 | D20: =IFERROR(_xlfn.XLOOKUP(A20,Dataset!E:E,Dataset!T:T),"Not Found") -> Returning
A21: Isha Patel | B21: =IFERROR(SUMIF(Dataset!E:E,A21,Dataset!Q:Q),0) -> 22294.24 | C21: =IFERROR(SUMIF(Dataset!E:E,A21,Dataset!L:L),0) -> 17 | D21: =IFERROR(_xlfn.XLOOKUP(A21,Dataset!E:E,Dataset!T:T),"Not Found") -> VIP
A22: Riya Shah | B22: =IFERROR(SUMIF(Dataset!E:E,A22,Dataset!Q:Q),0) -> 79947.47 | C22: =IFERROR(SUMIF(Dataset!E:E,A22,Dataset!L:L),0) -> 27 | D22: =IFERROR(_xlfn.XLOOKUP(A22,Dataset!E:E,Dataset!T:T),"Not Found") -> VIP
A23: Aditya Shah | B23: =IFERROR(SUMIF(Dataset!E:E,A23,Dataset!Q:Q),0) -> 32115.08 | C23: =IFERROR(SUMIF(Dataset!E:E,A23,Dataset!L:L),0) -> 17 | D23: =IFERROR(_xlfn.XLOOKUP(A23,Dataset!E:E,Dataset!T:T),"Not Found") -> New
A24: Vivaan Patel | B24: =IFERROR(SUMIF(Dataset!E:E,A24,Dataset!Q:Q),0) -> 26143.63 | C24: =IFERROR(SUMIF(Dataset!E:E,A24,Dataset!L:L),0) -> 18 | D24: =IFERROR(_xlfn.XLOOKUP(A24,Dataset!E:E,Dataset!T:T),"Not Found") -> Returning
A25: Kabir Patel | B25: =IFERROR(SUMIF(Dataset!E:E,A25,Dataset!Q:Q),0) -> 5110.29 | C25: =IFERROR(SUMIF(Dataset!E:E,A25,Dataset!L:L),0) -> 6 | D25: =IFERROR(_xlfn.XLOOKUP(A25,Dataset!E:E,Dataset!T:T),"Not Found") -> New
A26: Riya Patel | B26: =IFERROR(SUMIF(Dataset!E:E,A26,Dataset!Q:Q),0) -> 12355.93 | C26: =IFERROR(SUMIF(Dataset!E:E,A26,Dataset!L:L),0) -> 21 | D26: =IFERROR(_xlfn.XLOOKUP(A26,Dataset!E:E,Dataset!T:T),"Not Found") -> New
A27: Aarav Shah | B27: =IFERROR(SUMIF(Dataset!E:E,A27,Dataset!Q:Q),0) -> 3171.87 | C27: =IFERROR(SUMIF(Dataset!E:E,A27,Dataset!L:L),0) -> 7 | D27: =IFERROR(_xlfn.XLOOKUP(A27,Dataset!E:E,Dataset!T:T),"Not Found") -> VIP
A28: Priya Patel | B28: =IFERROR(SUMIF(Dataset!E:E,A28,Dataset!Q:Q),0) -> 7539.7 | C28: =IFERROR(SUMIF(Dataset!E:E,A28,Dataset!L:L),0) -> 7 | D28: =IFERROR(_xlfn.XLOOKUP(A28,Dataset!E:E,Dataset!T:T),"Not Found") -> New
A29: Mahi Patel | B29: =IFERROR(SUMIF(Dataset!E:E,A29,Dataset!Q:Q),0) -> 19485.15 | C29: =IFERROR(SUMIF(Dataset!E:E,A29,Dataset!L:L),0) -> 10 | D29: =IFERROR(_xlfn.XLOOKUP(A29,Dataset!E:E,Dataset!T:T),"Not Found") -> VIP
A30: Rohan Patel | B30: =IFERROR(SUMIF(Dataset!E:E,A30,Dataset!Q:Q),0) -> 3153.41 | C30: =IFERROR(SUMIF(Dataset!E:E,A30,Dataset!L:L),0) -> 5 | D30: =IFERROR(_xlfn.XLOOKUP(A30,Dataset!E:E,Dataset!T:T),"Not Found") -> Returning
A31: Meera Shah | B31: =IFERROR(SUMIF(Dataset!E:E,A31,Dataset!Q:Q),0) -> 1233.6 | C31: =IFERROR(SUMIF(Dataset!E:E,A31,Dataset!L:L),0) -> 8 | D31: =IFERROR(_xlfn.XLOOKUP(A31,Dataset!E:E,Dataset!T:T),"Not Found") -> New
A32: Jiya Patel | B32: =IFERROR(SUMIF(Dataset!E:E,A32,Dataset!Q:Q),0) -> 92235.3 | C32: =IFERROR(SUMIF(Dataset!E:E,A32,Dataset!L:L),0) -> 14 | D32: =IFERROR(_xlfn.XLOOKUP(A32,Dataset!E:E,Dataset!T:T),"Not Found") -> New
... A78: Dhruv Shah | B78: =IFERROR(SUMIF(Dataset!E:E,A78,Dataset!Q:Q),0) -> 13201.49 | C78: =IFERROR(SUMIF(Dataset!E:E,A78,Dataset!L:L),0) -> 10 | D78: =IFERROR(_xlfn.XLOOKUP(A78,Dataset!E:E,Dataset!T:T),"Not Found") -> New

Sheet ANALYSIS
A1: PRODUCT ANALYSIS
A3: UNIQUE PRODUCT | B3: UNITS SOLDS | C3: PRODUCT REVENUE | D3: PRODUCT PROFIT | E3: PURCHASE FREQUENCY | F3: AVERAGE RATING
A5: {=IFERROR(_xlfn._xlws.SORT(_xlfn.UNIQUE(Dataset!K2:K251)),"No Data")} -> Air Fryer | B5: =IFERROR(SUMIF(Dataset!K:K,A5,Dataset!L:L),0) -> 32 | C5: =IFERROR(SUMIF(Dataset!K:K,A5,Dataset!O:O),0) -> 189893.92 | D5: =IFERROR(SUMIF(Dataset!K:K,A5,Dataset!Q:Q),0) -> 56973.52 | E5: =IFERROR(COUNTIF(Dataset!K:K,A5),0) -> 10 | F5: =IFERROR(AVERAGEIF(Dataset!K:K,A5,Dataset!U:U),0) -> 4.3
A6: Backpack | B6: =IFERROR(SUMIF(Dataset!K:K,A6,Dataset!L:L),0) -> 40 | C6: =IFERROR(SUMIF(Dataset!K:K,A6,Dataset!O:O),0) -> 55768.73 | D6: =IFERROR(SUMIF(Dataset!K:K,A6,Dataset!Q:Q),0) -> 13950.73 | E6: =IFERROR(COUNTIF(Dataset!K:K,A6),0) -> 17 | F6: =IFERROR(AVERAGEIF(Dataset!K:K,A6,Dataset!U:U),0) -> 4.1764706
A7: Coffee | B7: =IFERROR(SUMIF(Dataset!K:K,A7,Dataset!L:L),0) -> 33 | C7: =IFERROR(SUMIF(Dataset!K:K,A7,Dataset!O:O),0) -> 13955.08 | D7: =IFERROR(SUMIF(Dataset!K:K,A7,Dataset!Q:Q),0) -> 3786.26 | E7: =IFERROR(COUNTIF(Dataset!K:K,A7),0) -> 11 | F7: =IFERROR(AVERAGEIF(Dataset!K:K,A7,Dataset!U:U),0) -> 4.0909091
A8: Dry Fruits | B8: =IFERROR(SUMIF(Dataset!K:K,A8,Dataset!L:L),0) -> 68 | C8: =IFERROR(SUMIF(Dataset!K:K,A8,Dataset!O:O),0) -> 59190.78 | D8: =IFERROR(SUMIF(Dataset!K:K,A8,Dataset!Q:Q),0) -> 17366.16 | E8: =IFERROR(COUNTIF(Dataset!K:K,A8),0) -> 20 | F8: =IFERROR(AVERAGEIF(Dataset!K:K,A8,Dataset!U:U),0) -> 4
A9: Face Wash | B9: =IFERROR(SUMIF(Dataset!K:K,A9,Dataset!L:L),0) -> 26 | C9: =IFERROR(SUMIF(Dataset!K:K,A9,Dataset!O:O),0) -> 10357.23 | D9: =IFERROR(SUMIF(Dataset!K:K,A9,Dataset!Q:Q),0) -> 3100.1 | E9: =IFERROR(COUNTIF(Dataset!K:K,A9),0) -> 9 | F9: =IFERROR(AVERAGEIF(Dataset!K:K,A9,Dataset!U:U),0) -> 4.1111111
A10: Green Tea | B10: =IFERROR(SUMIF(Dataset!K:K,A10,Dataset!L:L),0) -> 43 | C10: =IFERROR(SUMIF(Dataset!K:K,A10,Dataset!O:O),0) -> 12035.11 | D10: =IFERROR(SUMIF(Dataset!K:K,A10,Dataset!Q:Q),0) -> 3287.24 | E10: =IFERROR(COUNTIF(Dataset!K:K,A10),0) -> 14 | F10: =IFERROR(AVERAGEIF(Dataset!K:K,A10,Dataset!U:U),0) -> 4.0714286
A11: Headphones | B11: =IFERROR(SUMIF(Dataset!K:K,A11,Dataset!L:L),0) -> 41 | C11: =IFERROR(SUMIF(Dataset!K:K,A11,Dataset!O:O),0) -> 95380.34 | D11: =IFERROR(SUMIF(Dataset!K:K,A11,Dataset!Q:Q),0) -> 27735.28 | E11: =IFERROR(COUNTIF(Dataset!K:K,A11),0) -> 13 | F11: =IFERROR(AVERAGEIF(Dataset!K:K,A11,Dataset!U:U),0) -> 4.3076923
A12: Jeans | B12: =IFERROR(SUMIF(Dataset!K:K,A12,Dataset!L:L),0) -> 39 | C12: =IFERROR(SUMIF(Dataset!K:K,A12,Dataset!O:O),0) -> 66930.34 | D12: =IFERROR(SUMIF(Dataset!K:K,A12,Dataset!Q:Q),0) -> 20167.82 | E12: =IFERROR(COUNTIF(Dataset!K:K,A12),0) -> 13 | F12: =IFERROR(AVERAGEIF(Dataset!K:K,A12,Dataset!U:U),0) -> 4.3076923
A13: Laptop | B13: =IFERROR(SUMIF(Dataset!K:K,A13,Dataset!L:L),0) -> 79 | C13: =IFERROR(SUMIF(Dataset!K:K,A13,Dataset!O:O),0) -> 4068930.5 | D13: =IFERROR(SUMIF(Dataset!K:K,A13,Dataset!Q:Q),0) -> 1184750.7 | E13: =IFERROR(COUNTIF(Dataset!K:K,A13),0) -> 24 | F13: =IFERROR(AVERAGEIF(Dataset!K:K,A13,Dataset!U:U),0) -> 4.2083333
A14: Mixer Grinder | B14: =IFERROR(SUMIF(Dataset!K:K,A14,Dataset!L:L),0) -> 19 | C14: =IFERROR(SUMIF(Dataset!K:K,A14,Dataset!O:O),0) -> 59598.03 | D14: =IFERROR(SUMIF(Dataset!K:K,A14,Dataset!Q:Q),0) -> 17138.21 | E14: =IFERROR(COUNTIF(Dataset!K:K,A14),0) -> 7 | F14: =IFERROR(AVERAGEIF(Dataset!K:K,A14,Dataset!U:U),0) -> 4.1428571
A15: Perfume | B15: =IFERROR(SUMIF(Dataset!K:K,A15,Dataset!L:L),0) -> 4 | C15: =IFERROR(SUMIF(Dataset!K:K,A15,Dataset!O:O),0) -> 6428.64 | D15: =IFERROR(SUMIF(Dataset!K:K,A15,Dataset!Q:Q),0) -> 1747.55 | E15: =IFERROR(COUNTIF(Dataset!K:K,A15),0) -> 3 | F15: =IFERROR(AVERAGEIF(Dataset!K:K,A15,Dataset!U:U),0) -> 4.6666667
A16: Protein Bar | B16: =IFERROR(SUMIF(Dataset!K:K,A16,Dataset!L:L),0) -> 29 | C16: =IFERROR(SUMIF(Dataset!K:K,A16,Dataset!O:O),0) -> 6874.66 | D16: =IFERROR(SUMIF(Dataset!K:K,A16,Dataset!Q:Q),0) -> 1871.48 | E16: =IFERROR(COUNTIF(Dataset!K:K,A16),0) -> 10 | F16: =IFERROR(AVERAGEIF(Dataset!K:K,A16,Dataset!U:U),0) -> 4.2
A17: Shampoo | B17: =IFERROR(SUMIF(Dataset!K:K,A17,Dataset!L:L),0) -> 31 | C17: =IFERROR(SUMIF(Dataset!K:K,A17,Dataset!O:O),0) -> 15525.11 | D17: =IFERROR(SUMIF(Dataset!K:K,A17,Dataset!Q:Q),0) -> 4556.02 | E17: =IFERROR(COUNTIF(Dataset!K:K,A17),0) -> 9 | F17: =IFERROR(AVERAGEIF(Dataset!K:K,A17,Dataset!U:U),0) -> 4.3333333
... A24: Vacuum Cleaner | B24: =IFERROR(SUMIF(Dataset!K:K,A24,Dataset!L:L),0) -> 36 | C24: =IFERROR(SUMIF(Dataset!K:K,A24,Dataset!O:O),0) -> 304830.06 | D24: =IFERROR(SUMIF(Dataset!K:K,A24,Dataset!Q:Q),0) -> 75427.55 | E24: =IFERROR(COUNTIF(Dataset!K:K,A24),0) -> 12 | F24: =IFERROR(AVERAGEIF(Dataset!K:K,A24,Dataset!U:U),0) -> 4.6666667

Sheet PIVOT TABLE
A1: PIVOT TABLE
A4: Row Labels | B4: Sum of Revenue | C4: Sum of Quantity
A5: North | B5: 1906628.9 | C5: 112
A6: Air Fryer | B6: 63177.35 | C6: 11
A7: Backpack | B7: 4428.19 | C7: 3
A8: Coffee | B8: 2651.65 | C8: 6
A9: Dry Fruits | B9: 814.64 | C9: 1
A10: Face Wash | B10: 2102.9 | C10: 5
A11: Green Tea | B11: 1141.63 | C11: 4
A12: Jeans | B12: 3631.2 | C12: 2
A13: Laptop | B13: 1197316.7 | C13: 23
A14: Mixer Grinder | B14: 37097.52 | C14: 12
A15: Shampoo | B15: 5003.6 | C15: 10
A16: Smartphone | B16: 507557.11 | C16: 17
... A39: Grand Total | B39: 3639561.5 | C39: 292

Sheet CHARTS
