Workbook

Sheet Sales_Data
A1: SaleID | B1: CustomerID | C1: CustomerName | D1: Region | E1: Product | F1: Category | G1: Sales | H1: Cost | I1: Discount | J1: Profit | K1: Date | L1: Quantity
A2: S001 | B2: C111 | C2: Arjun | D2: West | E2: Laptop | F2: Electronics | G2: 97496 | H2: 55939 | I2: 7 | J2: 34732.28 | K2: 46212 | L2: 3
A3: S002 | B3: C102 | C3: Priya | D3: West | E3: Keyboard | F3: Accessories | G3: 55602 | H3: 25816 | I3: 2 | J3: 28673.96 | K3: 46083 | L3: 4
A4: S003 | B4: C109 | C4: Dev | D4: West | E4: Keyboard | F4: Accessories | G4: 26362 | H4: 20356 | I4: 22 | J4: 206.36 | K4: 46131 | L4: 9
A5: S004 | B5: C104 | C5: Neha | D5: East | E5: Keyboard | F5: Accessories | G5: 36763 | H5: 29934 | I5: 0 | J5: 6829 | K5: 46202 | L5: 3
A6: S005 | B6: C107 | C6: Karan | D6: North | E6: Tablet | F6: Electronics | G6: 20679 | H6: 11309 | I6: 24 | J6: 4407.04 | K6: 46050 | L6: 6
A7: S006 | B7: C102 | C7: Priya | D7: East | E7: Laptop | F7: Electronics | G7: 47352 | H7: 39367 | I7: 19 | J7: -1011.88 | K7: 46230 | L7: 5
A8: S007 | B8: C101 | C8: Rahul | D8: East | E8: Keyboard | F8: Accessories | G8: 16661 | H8: 14793 | I8: 12 | J8: -131.32 | K8: 46165 | L8: 2
A9: S008 | B9: C105 | C9: Jay | D9: North | E9: Keyboard | F9: Accessories | G9: 25503 | H9: 19562 | I9: 1 | J9: 5685.97 | K9: 46221 | L9: 4
A10: S009 | B10: C105 | C10: Jay | D10: West | E10: Headphones | F10: Accessories | G10: 30812 | H10: 25879 | I10: 12 | J10: 1235.56 | K10: 46140 | L10: 5
A11: S010 | B11: C111 | C11: Arjun | D11: North | E11: Mobile | F11: Electronics | G11: 48820 | H11: 29773 | I11: 21 | J11: 8794.8 | K11: 46203 | L11: 5
A12: S011 | B12: C115 | C12: Vivek | D12: West | E12: Keyboard | F12: Accessories | G12: 83527 | H12: 44019 | I12: 23 | J12: 20296.79 | K12: 46065 | L12: 4
A13: S012 | B13: C108 | C13: Riya | D13: East | E13: Tablet | F13: Electronics | G13: 84186 | H13: 63953 | I13: 7 | J13: 14339.98 | K13: 46239 | L13: 6
... A251: S250 | B251: C101 | C251: Rahul | D251: North | E251: Headphones | F251: Accessories | G251: 62225 | H251: 47492 | I251: 4 | J251: 12244 | K251: 46138 | L251: 8

Sheet Analysis
B2: 1.Top 10 Customers – Total Purchase | G2: 2.WHAT-IF Analysis
B4: CUSTOMER ID | C4: NAME | D4: TOTAL PURCHASE | G4: DISCOUNT | H4: TOTAL PROFIT
B5: {=_xlfn.UNIQUE(Sales_Data!B2:B251)} -> C111 | C5: =_xlfn.XLOOKUP(B5,Sales_Data!B:B,Sales_Data!C:C) -> Arjun | D5: =SUMIF(Sales_Data!B:B,B5,Sales_Data!G:G) -> 1202281 | G5: 0 | H5: {=SUMPRODUCT(Sales_Data!G2:G251-Sales_Data!H2:H251-(Sales_Data!G2:G251*E11))} -> 3836093
B6: C102 | C6: =_xlfn.XLOOKUP(B6,Sales_Data!B:B,Sales_Data!C:C) -> Priya | D6: =SUMIF(Sales_Data!B:B,B6,Sales_Data!G:G) -> 735182 | G6: 0.05 | H6: {=SUMPRODUCT(Sales_Data!G3:G252-Sales_Data!H3:H252-(Sales_Data!G3:G252*E12))} -> 3794536
B7: C109 | C7: =_xlfn.XLOOKUP(B7,Sales_Data!B:B,Sales_Data!C:C) -> Dev | D7: =SUMIF(Sales_Data!B:B,B7,Sales_Data!G:G) -> 861185 | G7: 0.1 | H7: {=SUMPRODUCT(Sales_Data!G4:G253-Sales_Data!H4:H253-(Sales_Data!G4:G253*E13))} -> 3764750
B8: C104 | C8: =_xlfn.XLOOKUP(B8,Sales_Data!B:B,Sales_Data!C:C) -> Neha | D8: =SUMIF(Sales_Data!B:B,B8,Sales_Data!G:G) -> 624849 | G8: 0.15 | H8: {=SUMPRODUCT(Sales_Data!G5:G254-Sales_Data!H5:H254-(Sales_Data!G5:G254*E14))} -> 3758744
B9: C107 | C9: =_xlfn.XLOOKUP(B9,Sales_Data!B:B,Sales_Data!C:C) -> Karan | D9: =SUMIF(Sales_Data!B:B,B9,Sales_Data!G:G) -> 621620 | G9: 0.2 | H9: {=SUMPRODUCT(Sales_Data!G6:G255-Sales_Data!H6:H255-(Sales_Data!G6:G255*E15))} -> 3751915
B10: C101 | C10: =_xlfn.XLOOKUP(B10,Sales_Data!B:B,Sales_Data!C:C) -> Rahul | D10: =SUMIF(Sales_Data!B:B,B10,Sales_Data!G:G) -> 875459 | G10: 0.25 | H10: {=SUMPRODUCT(Sales_Data!G7:G256-Sales_Data!H7:H256-(Sales_Data!G7:G256*E16))} -> 3742545
B11: C105 | C11: =_xlfn.XLOOKUP(B11,Sales_Data!B:B,Sales_Data!C:C) -> Jay | D11: =SUMIF(Sales_Data!B:B,B11,Sales_Data!G:G) -> 1393310 | G11: 0.3 | H11: {=SUMPRODUCT(Sales_Data!G8:G257-Sales_Data!H8:H257-(Sales_Data!G8:G257*E17))} -> 3734560
B12: C115 | C12: =_xlfn.XLOOKUP(B12,Sales_Data!B:B,Sales_Data!C:C) -> Vivek | D12: =SUMIF(Sales_Data!B:B,B12,Sales_Data!G:G) -> 1015197 | G12: 0.35 | H12: {=SUMPRODUCT(Sales_Data!G9:G258-Sales_Data!H9:H258-(Sales_Data!G9:G258*E18))} -> 3732692
B13: C108 | C13: =_xlfn.XLOOKUP(B13,Sales_Data!B:B,Sales_Data!C:C) -> Riya | D13: =SUMIF(Sales_Data!B:B,B13,Sales_Data!G:G) -> 1013143 | G13: 0.4 | H13: {=SUMPRODUCT(Sales_Data!G10:G259-Sales_Data!H10:H259-(Sales_Data!G10:G259*E19))} -> 3726751
B14: C113 | C14: =_xlfn.XLOOKUP(B14,Sales_Data!B:B,Sales_Data!C:C) -> Rohan | D14: =SUMIF(Sales_Data!B:B,B14,Sales_Data!G:G) -> 980219 | G14: 0.45 | H14: {=SUMPRODUCT(Sales_Data!G11:G260-Sales_Data!H11:H260-(Sales_Data!G11:G260*E20))} -> 3721818
B15: C112 | C15: =_xlfn.XLOOKUP(B15,Sales_Data!B:B,Sales_Data!C:C) -> Kavya | D15: =SUMIF(Sales_Data!B:B,B15,Sales_Data!G:G) -> 885563 | G15: 0.5 | H15: {=SUMPRODUCT(Sales_Data!G12:G261-Sales_Data!H12:H261-(Sales_Data!G12:G261*E21))} -> 3702771
B16: C110 | C16: =_xlfn.XLOOKUP(B16,Sales_Data!B:B,Sales_Data!C:C) -> Isha | D16: =SUMIF(Sales_Data!B:B,B16,Sales_Data!G:G) -> 380323 | G16: 0.55 | H16: {=SUMPRODUCT(Sales_Data!G13:G262-Sales_Data!H13:H262-(Sales_Data!G13:G262*C22))} -> 3663263
B17: C114 | C17: =_xlfn.XLOOKUP(B17,Sales_Data!B:B,Sales_Data!C:C) -> Anjali | D17: =SUMIF(Sales_Data!B:B,B17,Sales_Data!G:G) -> 169478 | G17: 0.6 | H17: {=SUMPRODUCT(Sales_Data!G14:G263-Sales_Data!H14:H263-(Sales_Data!G14:G263*E23))} -> 3643030
B18: C106 | C18: =_xlfn.XLOOKUP(B18,Sales_Data!B:B,Sales_Data!C:C) -> Meera | D18: =SUMIF(Sales_Data!B:B,B18,Sales_Data!G:G) -> 790274 | G18: 0.65 | H18: {=SUMPRODUCT(Sales_Data!G15:G264-Sales_Data!H15:H264-(Sales_Data!G15:G264*E24))} -> 3642183
B19: C103 | C19: =_xlfn.XLOOKUP(B19,Sales_Data!B:B,Sales_Data!C:C) -> Amit | D19: =SUMIF(Sales_Data!B:B,B19,Sales_Data!G:G) -> 569478 | G19: 0.7 | H19: {=SUMPRODUCT(Sales_Data!G16:G265-Sales_Data!H16:H265-(Sales_Data!G16:G265*E25))} -> 3614135

Sheet Descriptive_Stats
B1: Descriptive Status
A8: Sales
A10: Mean | B10: 48470.244
A11: Standard Error | B11: 1839.6758
A12: Median | B12: 48777
A13: Mode | B13: #N/A
A14: Standard Deviation | B14: 29087.828
A15: Sample Variance | B15: 8.4610174e+08
A16: Kurtosis | B16: -1.2596133
A17: Skewness | B17: 0.036539884
A18: Range | B18: 98550
A19: Minimum | B19: 636
A20: Maximum | B20: 99186
A21: Sum | B21: 12117561
A22: Count | B22: 250

Sheet Regression
A1: Summary Output
A3: Regression Statistics
A4: Multiple R | B4: 0.54704699
A5: R Square | B5: 0.29926041
A6: Adjusted R Square | B6: 0.29643484
A7: Standard Error | B7: 7966.4861
A8: Observations | B8: 250
A11: ANOVA | B11: df | C11: SS | D11: MS | E11: F | F11: Significance F
A12: Regression | B12: 1 | C12: 6.721681e+09 | D12: 6.721681e+09 | E12: 105.91178 | F12: 6.4758946e-21
A13: Residual | B13: 248 | C13: 1.5739295e+10 | D13: 63464901
A14: Total | B14: 249 | C14: 2.2460976e+10
B16: Coefficients | C16: Standard Error | D16: t Stat | E16: P-value | F16: Lower 95% | G16: Upper 95% | H16: Lower 95.0% | I16: Upper 95.0%
A17: Intercept | B17: -290.88544 | C17: 980.60216 | D17: -0.2966396 | E17: 0.76698995 | F17: -2222.2556 | G17: 1640.4847 | H17: -2222.2556 | I17: 1640.4847
A18: Sales | B18: 0.17861913 | C18: 0.017356248 | D18: 10.291345 | E18: 6.4758946e-21 | F18: 0.14443469 | G18: 0.21280358 | H18: 0.14443469 | I18: 0.21280358
A23: Total Customer By Total Purchase
A28: Customer Name | B28: Total Purchase | C28: Total Profit
A29: {=_xlfn.UNIQUE(Sales_Data!C2:C51)} -> Arjun | B29: =SUMIF(Sales_Data!$C$2:$C$251,A29,Sales_Data!$G$2:$G$251) -> 1202281 | C29: =SUMIF(Sales_Data!$C$2:$C$251,Regression!A29,Sales_Data!$J$2:$J$251) -> 230257.17
A30: Priya | B30: =SUMIF(Sales_Data!$C$2:$C$251,A30,Sales_Data!$G$2:$G$251) -> 735182 | C30: =SUMIF(Sales_Data!$C$2:$C$251,Regression!A30,Sales_Data!$J$2:$J$251) -> 117874.91
A31: Dev | B31: =SUMIF(Sales_Data!$C$2:$C$251,A31,Sales_Data!$G$2:$G$251) -> 861185 | C31: =SUMIF(Sales_Data!$C$2:$C$251,Regression!A31,Sales_Data!$J$2:$J$251) -> 131965.35
A32: Neha | B32: =SUMIF(Sales_Data!$C$2:$C$251,A32,Sales_Data!$G$2:$G$251) -> 624849 | C32: =SUMIF(Sales_Data!$C$2:$C$251,Regression!A32,Sales_Data!$J$2:$J$251) -> 145863.33
A33: Karan | B33: =SUMIF(Sales_Data!$C$2:$C$251,A33,Sales_Data!$G$2:$G$251) -> 621620 | C33: =SUMIF(Sales_Data!$C$2:$C$251,Regression!A33,Sales_Data!$J$2:$J$251) -> 133982.7
A34: Rahul | B34: =SUMIF(Sales_Data!$C$2:$C$251,A34,Sales_Data!$G$2:$G$251) -> 875459 | C34: =SUMIF(Sales_Data!$C$2:$C$251,Regression!A34,Sales_Data!$J$2:$J$251) -> 221881.69
A35: Jay | B35: =SUMIF(Sales_Data!$C$2:$C$251,A35,Sales_Data!$G$2:$G$251) -> 1393310 | C35: =SUMIF(Sales_Data!$C$2:$C$251,Regression!A35,Sales_Data!$J$2:$J$251) -> 241395.23
A36: Vivek | B36: =SUMIF(Sales_Data!$C$2:$C$251,A36,Sales_Data!$G$2:$G$251) -> 1015197 | C36: =SUMIF(Sales_Data!$C$2:$C$251,Regression!A36,Sales_Data!$J$2:$J$251) -> 145058.76
A37: Riya | B37: =SUMIF(Sales_Data!$C$2:$C$251,A37,Sales_Data!$G$2:$G$251) -> 1013143 | C37: =SUMIF(Sales_Data!$C$2:$C$251,Regression!A37,Sales_Data!$J$2:$J$251) -> 140638.36
A38: Rohan | B38: =SUMIF(Sales_Data!$C$2:$C$251,A38,Sales_Data!$G$2:$G$251) -> 980219 | C38: =SUMIF(Sales_Data!$C$2:$C$251,Regression!A38,Sales_Data!$J$2:$J$251) -> 171759.44
A39: Kavya | B39: =SUMIF(Sales_Data!$C$2:$C$251,A39,Sales_Data!$G$2:$G$251) -> 885563 | C39: =SUMIF(Sales_Data!$C$2:$C$251,Regression!A39,Sales_Data!$J$2:$J$251) -> 146805.57
A40: Isha | B40: =SUMIF(Sales_Data!$C$2:$C$251,A40,Sales_Data!$G$2:$G$251) -> 380323 | C40: =SUMIF(Sales_Data!$C$2:$C$251,Regression!A40,Sales_Data!$J$2:$J$251) -> 74193.87
A41: Anjali | B41: =SUMIF(Sales_Data!$C$2:$C$251,A41,Sales_Data!$G$2:$G$251) -> 169478 | C41: =SUMIF(Sales_Data!$C$2:$C$251,Regression!A41,Sales_Data!$J$2:$J$251) -> 14424.65
... A43: Amit | B43: =SUMIF(Sales_Data!$C$2:$C$251,A43,Sales_Data!$G$2:$G$251) -> 569478 | C43: =SUMIF(Sales_Data!$C$2:$C$251,Regression!A43,Sales_Data!$J$2:$J$251) -> 69804.05

Sheet Monthly_Sales
A1: Monthly Sales Growth
A3: Month | B3: Total Sales | C3: Growth vs Sales Growth
A4: =DATE(2026,1,1) -> 46023 | B4: =SUMIFS(Sales_Data!$G$2:$G$251,Sales_Data!$K$2:$K$251,">="&A4,Sales_Data!$K$2:$K$251,"<"&EDATE(A4,1)) -> 1326612 | C4: =(B5-B4)/B4 -> -0.16850745
A5: =EDATE(A4,1) -> 46054 | B5: =SUMIFS(Sales_Data!$G$2:$G$251,Sales_Data!$K$2:$K$251,">="&A5,Sales_Data!$K$2:$K$251,"<"&EDATE(A5,1)) -> 1103068 | C5: =(B6-B5)/B5 -> 0.18908354
A6: =EDATE(A5,1) -> 46082 | B6: =SUMIFS(Sales_Data!$G$2:$G$251,Sales_Data!$K$2:$K$251,">="&A6,Sales_Data!$K$2:$K$251,"<"&EDATE(A6,1)) -> 1311640 | C6: =(B7-B6)/B6 -> 0.21710607
A7: =EDATE(A6,1) -> 46113 | B7: =SUMIFS(Sales_Data!$G$2:$G$251,Sales_Data!$K$2:$K$251,">="&A7,Sales_Data!$K$2:$K$251,"<"&EDATE(A7,1)) -> 1596405 | C7: =(B8-B7)/B7 -> -0.30783041
A8: =EDATE(A7,1) -> 46143 | B8: =SUMIFS(Sales_Data!$G$2:$G$251,Sales_Data!$K$2:$K$251,">="&A8,Sales_Data!$K$2:$K$251,"<"&EDATE(A8,1)) -> 1104983 | C8: =(B9-B8)/B8 -> 0.19351429
A9: =EDATE(A8,1) -> 46174 | B9: =SUMIFS(Sales_Data!$G$2:$G$251,Sales_Data!$K$2:$K$251,">="&A9,Sales_Data!$K$2:$K$251,"<"&EDATE(A9,1)) -> 1318813 | C9: =(B10-B9)/B9 -> 0.21219309
A10: =EDATE(A9,1) -> 46204 | B10: =SUMIFS(Sales_Data!$G$2:$G$251,Sales_Data!$K$2:$K$251,">="&A10,Sales_Data!$K$2:$K$251,"<"&EDATE(A10,1)) -> 1598656 | C10: =(B11-B10)/B10 -> 0.36926331
A11: =EDATE(A10,1) -> 46235 | B11: =SUMIFS(Sales_Data!$G$2:$G$251,Sales_Data!$K$2:$K$251,">="&A11,Sales_Data!$K$2:$K$251,"<"&EDATE(A11,1)) -> 2188981 | C11: =(B12-B11)/B11 -> -0.74033443
A12: =EDATE(A11,1) -> 46266 | B12: =SUMIFS(Sales_Data!$G$2:$G$251,Sales_Data!$K$2:$K$251,">="&A12,Sales_Data!$K$2:$K$251,"<"&EDATE(A12,1)) -> 568403 | C12: =(B13-B12)/B12 -> -1

Sheet Top Customer
A1: High - Value Customers
A3: Rank | B3: Customer Name | C3: Total Purchase | D3: Region
A5: 1 | B5: {=_xlfn.LET( _xlpm.customers,_xlfn.UNIQUE(Sales_Data!C2:C251), _xlpm.purchase,SUMIF(Sales_Data!C2:C251,_xlpm.customers,Sales_Data!G2:G251), _xlfn.TAKE(_xlfn.SORTBY(_xlpm.customers,_xlpm.purchase,-1),10) )} -> Jay | C5: =SUMIF(Sales_Data!$C$2:$C$251,B5,Sales_Data!$G$2:$G$251) -> 1393310 | D5: =_xlfn.XLOOKUP(B5,Sales_Data!$C$2:$C$251,Sales_Data!$D$2:$D$251) -> North
A6: 2 | B6: Arjun | C6: =SUMIF(Sales_Data!$C$2:$C$251,B6,Sales_Data!$G$2:$G$251) -> 1202281 | D6: =_xlfn.XLOOKUP(B6,Sales_Data!$C$2:$C$251,Sales_Data!$D$2:$D$251) -> West
A7: 3 | B7: Vivek | C7: =SUMIF(Sales_Data!$C$2:$C$251,B7,Sales_Data!$G$2:$G$251) -> 1015197 | D7: =_xlfn.XLOOKUP(B7,Sales_Data!$C$2:$C$251,Sales_Data!$D$2:$D$251) -> West
A8: 4 | B8: Riya | C8: =SUMIF(Sales_Data!$C$2:$C$251,B8,Sales_Data!$G$2:$G$251) -> 1013143 | D8: =_xlfn.XLOOKUP(B8,Sales_Data!$C$2:$C$251,Sales_Data!$D$2:$D$251) -> East
A9: 5 | B9: Rohan | C9: =SUMIF(Sales_Data!$C$2:$C$251,B9,Sales_Data!$G$2:$G$251) -> 980219 | D9: =_xlfn.XLOOKUP(B9,Sales_Data!$C$2:$C$251,Sales_Data!$D$2:$D$251) -> West
A10: 6 | B10: Kavya | C10: =SUMIF(Sales_Data!$C$2:$C$251,B10,Sales_Data!$G$2:$G$251) -> 885563 | D10: =_xlfn.XLOOKUP(B10,Sales_Data!$C$2:$C$251,Sales_Data!$D$2:$D$251) -> North
A11: 7 | B11: Rahul | C11: =SUMIF(Sales_Data!$C$2:$C$251,B11,Sales_Data!$G$2:$G$251) -> 875459 | D11: =_xlfn.XLOOKUP(B11,Sales_Data!$C$2:$C$251,Sales_Data!$D$2:$D$251) -> East
A12: 8 | B12: Dev | C12: =SUMIF(Sales_Data!$C$2:$C$251,B12,Sales_Data!$G$2:$G$251) -> 861185 | D12: =_xlfn.XLOOKUP(B12,Sales_Data!$C$2:$C$251,Sales_Data!$D$2:$D$251) -> West
A13: 9 | B13: Meera | C13: =SUMIF(Sales_Data!$C$2:$C$251,B13,Sales_Data!$G$2:$G$251) -> 790274 | D13: =_xlfn.XLOOKUP(B13,Sales_Data!$C$2:$C$251,Sales_Data!$D$2:$D$251) -> North
A14: 10 | B14: Priya | C14: =SUMIF(Sales_Data!$C$2:$C$251,B14,Sales_Data!$G$2:$G$251) -> 735182 | D14: =_xlfn.XLOOKUP(B14,Sales_Data!$C$2:$C$251,Sales_Data!$D$2:$D$251) -> West
A16: Customer Above Overall Purchase Average
A18: Average Purchase | C18: =AVERAGE(C4:C13) -> 1001847.9
A19: Count | C19: =COUNTIF(C4:C13,">"&AVERAGE(C4:C13)) -> 4

Sheet Pivot Table
B1: Column Labels
B2: Headphones | D2: Keyboard | F2: Laptop | H2: Mobile | J2: Monitor | L2: Mouse | N2: Tablet | P2: Total Sum of Sales | Q2: Total Sum of Sales2
A3: Row Labels | B3: Sum of Sales | C3: Sum of Sales2 | D3: Sum of Sales | E3: Sum of Sales2 | F3: Sum of Sales | G3: Sum of Sales2 | H3: Sum of Sales | I3: Sum of Sales2 | J3: Sum of Sales | K3: Sum of Sales2 | L3: Sum of Sales | M3: Sum of Sales2 | N3: Sum of Sales | O3: Sum of Sales2
A4: East | B4: 411805 | C4: 411805 | D4: 364400 | E4: 364400 | F4: 477709 | G4: 477709 | H4: 206776 | I4: 206776 | J4: 465474 | K4: 465474 | L4: 418610 | M4: 418610 | N4: 765125 | O4: 765125 | P4: 3109899 | Q4: 3109899
A5: North | B5: 772409 | C5: 772409 | D5: 621174 | E5: 621174 | F5: 462328 | G5: 462328 | H5: 425728 | I5: 425728 | J5: 459829 | K5: 459829 | L5: 171692 | M5: 171692 | N5: 259895 | O5: 259895 | P5: 3173055 | Q5: 3173055
A6: South | B6: 633986 | C6: 633986 | D6: 407872 | E6: 407872 | F6: 311823 | G6: 311823 | H6: 531009 | I6: 531009 | J6: 621677 | K6: 621677 | L6: 479061 | M6: 479061 | N6: 242195 | O6: 242195 | P6: 3227623 | Q6: 3227623
A7: West | B7: 428373 | C7: 428373 | D7: 598822 | E7: 598822 | F7: 284417 | G7: 284417 | H7: 291187 | I7: 291187 | J7: 343668 | K7: 343668 | L7: 425052 | M7: 425052 | N7: 235465 | O7: 235465 | P7: 2606984 | Q7: 2606984
A8: Grand Total | B8: 2246573 | C8: 2246573 | D8: 1992268 | E8: 1992268 | F8: 1536277 | G8: 1536277 | H8: 1454700 | I8: 1454700 | J8: 1890648 | K8: 1890648 | L8: 1494415 | M8: 1494415 | N8: 1502680 | O8: 1502680 | P8: 12117561 | Q8: 12117561

Sheet Charts
A1: Charts
